gni-0.1.4.dist-info/METADATA
gni-0.1.4.dist-info/WHEEL
gni-0.1.4.dist-info/licenses/LICENSE
gni_lib/__init__.py
gni_lib/gni_lib.abi3.so
gni-0.1.4.dist-info/RECORD
