Metadata-Version: 2.4
Name: gni
Version: 0.1.4
Requires-Dist: cffi
License-File: LICENSE
Summary: Library to create a GPU Node ID
Author: Lucca Bertoncini
Author-email: luccab@meta.com
Maintainer-email: Lucca Bertoncini <luccab@meta.com>
License: Apache-2.0
Requires-Python: >=3.8
Project-URL: Homepage, https://github.com/facebookresearch/gni
Project-URL: Issues, https://github.com/facebookresearch/gni/issues
